aioproxyline/__init__.py
aioproxyline/core/__init__.py
aioproxyline/core/abc/__init__.py
aioproxyline/core/abc/client.py
aioproxyline/core/client.py
aioproxyline/core/methods/__init__.py
aioproxyline/core/methods/balance.py
aioproxyline/core/methods/base.py
aioproxyline/core/methods/order.py
aioproxyline/core/methods/other.py
aioproxyline/core/methods/proxy.py
aioproxyline/exceptions/__init__.py
aioproxyline/exceptions/authentication.py
aioproxyline/exceptions/base.py
aioproxyline/types/__init__.py
aioproxyline/types/balance.py
aioproxyline/types/countries.py
aioproxyline/types/enum.py
aioproxyline/types/ips.py
aioproxyline/types/order.py
aioproxyline/types/proxy_list.py
aioproxyline-1.1.2.dist-info/LICENSE
aioproxyline-1.1.2.dist-info/WHEEL
aioproxyline-1.1.2.dist-info/METADATA
aioproxyline-1.1.2.dist-info/RECORD
